DeleteFilesRapidly/DeleteFiles.py
DeleteFilesRapidly/__init__.py
DeleteFilesRapidly-0.0.6.dist-info/LICENSE.txt
DeleteFilesRapidly-0.0.6.dist-info/METADATA
DeleteFilesRapidly-0.0.6.dist-info/WHEEL
DeleteFilesRapidly-0.0.6.dist-info/top_level.txt
DeleteFilesRapidly-0.0.6.dist-info/RECORD
