Metadata-Version: 2.1
Name: DeleteFilesRapidly
Version: 0.0.6
Summary: Tool for quickly deleting files on a remote server via threading
Home-page: https://github.com/brianmanderson/DeleteFilesRapidly
Author: Brian Mark Anderson
Author-email: b5anderson@health.ucsd.edu
License: UNKNOWN
Platform: UNKNOWN
Classifier: Programming Language :: Python :: 3
Classifier: License :: OSI Approved :: GNU Affero General Public License v3
License-File: LICENSE.txt
